Metadata-Version: 1.0
Name: similar-words-vz
Version: 0.2
Summary: Looking for similar words in Bible.
Home-page: UNKNOWN
Author: UNKNOWN
Author-email: vl.sergiiy@gmail.com
License: UNKNOWN
Platform: UNKNOWN
